{"tld":"academy","tldUpdated":1587081600000,"tldCreated":1386806400000,"whoisServer":["whois.nic.academy"],"registry":"http://www.donuts.domains/","ianaUrl":"https://www.iana.org/domains/root/db/academy.html","t":1622032003398,"version":1,"sampleDomains":{"academy":["cybertalk.academy","sarmayedigital.academy","hadaf.academy","faramouj.academy","thehealthcareleadership.academy","hamrah.academy","ramantech.academy","rastava.academy","3dmax.academy","cto.academy","halakoei.academy","thenational.academy","dryoutube.academy","farin.academy","diy.academy","voila.academy","cyberbet.academy","im.academy","arzamas.academy","websima.academy"]},"type":"generic","isIDN":false,"rdapServers":["https://rdap.donuts.co/rdap/domain/"],"rdapUpdated":1622033129100}