{"tld":"academy","tldUpdated":1635897600000,"tldCreated":1386806400000,"whoisServer":["whois.nic.academy"],"registry":"http://www.donuts.domains/","ianaUrl":"https://www.iana.org/domains/root/db/academy.html","t":1651162863105,"version":1,"sampleDomains":{"academy":["spanish.academy","hamrah.academy","farin.academy","hype4.academy","websima.academy","typing.academy","g2o.academy","ramzarz.academy","hadaf.academy","lifedrawing.academy","rahbaran.academy","businessplus.academy","forex.academy","efl.academy","astirik.academy","kaman.academy","arcade.academy","modir.academy","calculator.academy","arzamas.academy"]},"type":"generic","isIDN":false,"rdapServers":["https://rdap.donuts.co/rdap/domain/"],"rdapUpdated":1651162099751}