{"tld":"al","tldUpdated":1501891200000,"tldCreated":703814400000,"whoisServer":[],"registry":"http://www.akep.al/sq/regjistrim-domain","ianaUrl":"https://www.iana.org/domains/root/db/al.html","t":1672688302509,"version":1,"sampleDomains":{"al":["camstars.al","sl.al","bere.al","zib.al","tirexo.al","anonib.al","jbteen.al","teenfolder.al","selfiecams.al","french-stream.al","dapim.al","gfriend.al","gfriendz.al","wgirlz.al","girlshub.al","tid.al","merrjep.al","jfraction.al","trib.al","exit.al"],"gov.al":["njose.gov.al","fsdksh.gov.al","planifikimi.gov.al","pp.gov.al","shendetesia.gov.al","tatime.gov.al","ata.gov.al","instat.gov.al","financa.gov.al","e-albania.gov.al","rinia.gov.al","dap.gov.al","ipard.gov.al","dogana.gov.al","akshi.gov.al","asig.gov.al","qkb.gov.al","konsultimipublik.gov.al","tkob.gov.al","bashkiashkoder.gov.al"],"com.al":["airalbania.com.al","gjej-produktin-zejtar.com.al","shekulli.com.al","bkt.com.al","kaleshi.com.al","asdental.com.al","amcham.com.al","freelancer.com.al","mesazhi.com.al","shendeti.com.al","shqiperiaime.com.al","panorama.com.al","cogent.com.al","sigal.com.al","aasf.com.al","alfa.com.al","uba.com.al","procreditbank.com.al","udheto.com.al","sot.com.al"],"mil.al":["aaf.mil.al","tradoc.mil.al"],"edu.al":["fgjm.edu.al","actirana.edu.al","ubt.edu.al","unishk.edu.al","luarasi-univ.edu.al","umsh.edu.al","fau.edu.al","uamd.edu.al","uniel.edu.al","fshs-ut.edu.al","beder.edu.al","fgjh.edu.al","albanianuniversity.edu.al","umed.edu.al","epoka.edu.al","geo.edu.al","ual.edu.al","unitir.edu.al","uet.edu.al","univlora.edu.al"],"org.al":["klsh.org.al","dhka.org.al","soskd.org.al","ara.org.al","cec.org.al","acpd.org.al","nesmark.org.al","pameca.org.al","observator.org.al","ahc.org.al","dhkz.org.al","astes.org.al","esa.org.al","adrf.org.al","respublica.org.al","shosh.org.al","tlas.org.al","ama.org.al","aidharmonisation.org.al","edupro.org.al"]},"type":"cctld","isIDN":false,"rdapServers":[],"rdapUpdated":1658865545803}