{"tld":"as","tldUpdated":1607817600000,"tldCreated":866073600000,"whoisServer":["whois.nic.as"],"registry":"http://www.nic.as","ianaUrl":"https://www.iana.org/domains/root/db/as.html","t":1627476004796,"version":1,"sampleDomains":{"as":["hoo.as","habd.as","tales.as","huobi.as","uwatchfree.as","smrt.as","cge.as","nyl.as","1234.as","opr.as","chi.as","origami.as","snap.as","write.as","4movierulz.as","c-i.as","b-ok.as","mid.as","google.as","mnm.as"]},"type":"cctld","isIDN":false,"rdapServers":[],"rdapUpdated":1627477259016}