{"tld":"attorney","tldUpdated":1635292800000,"tldCreated":1400716800000,"whoisServer":["whois.nic.attorney"],"registry":"http://www.donuts.domains/","ianaUrl":"https://www.iana.org/domains/root/db/attorney.html","t":1652311912835,"version":1,"sampleDomains":{"attorney":["luxburgcarolath.attorney","techlaw.attorney","sinitsa.attorney","best-divorce.attorney","theorlandoforeclosure.attorney","c0d3.attorney","nagel.attorney","demircihukuk.attorney","johnhelms.attorney","panhandlecriminaldefense.attorney","nearme.attorney","eb5.attorney","amazonsellers.attorney","familybankruptcy.attorney","anwalt-zuerich.attorney","gutierrezinjury.attorney","cac.attorney","laurenellis.attorney","newyorkdebtcollection.attorney","zwickel.attorney"]},"type":"generic","isIDN":false,"rdapServers":["https://rdap.donuts.co/rdap/domain/"],"rdapUpdated":1652312200786}