{"tld":"br","tldUpdated":1564617600000,"tldCreated":608860800000,"whoisServer":["whois.registro.br"],"registry":"http://registro.br/","ianaUrl":"https://www.iana.org/domains/root/db/br.html","t":1641148388672,"version":1,"sampleDomains":{"com.br":["olx.com.br","lackinprivacy.com.br","uol.com.br","portaldoholanda.com.br","imirante.com.br","videotecaead.com.br","claro.com.br","google.com.br","eldarya.com.br","politicadistrital.com.br","amigosecreto.com.br","altoqi.com.br","sociparques.com.br","flashscore.com.br","checklistfacil.com.br","the-west.com.br","metropolitanafm.com.br","opiniaobomvaleapena.com.br","ballroom.com.br","americanas.com.br"],"df.gov.br":["transparencia.df.gov.br","codeplan.df.gov.br","trabalho.df.gov.br","seduh.df.gov.br","caesb.df.gov.br","dodf.df.gov.br","seape.df.gov.br","egov.df.gov.br","sistemas.df.gov.br","notalegal.df.gov.br","fazenda.df.gov.br","codhab.df.gov.br","gdfnet.df.gov.br","saude.df.gov.br","agenciabrasilia.df.gov.br","adgdf.df.gov.br","sejus.df.gov.br","economia.df.gov.br","detran.df.gov.br","riachofundo1.df.gov.br"],"sp.gov.br":["cps.sp.gov.br","vreredesim.sp.gov.br","policiamilitar.sp.gov.br","fundacc.sp.gov.br","detran.sp.gov.br","fazenda.sp.gov.br","apiai.sp.gov.br","camposdojordao.sp.gov.br","spsempapel.sp.gov.br","jucesp.sp.gov.br","vacinaja.sp.gov.br","campinas.sp.gov.br","ima.sp.gov.br","prefeitura.sp.gov.br","poupatempo.sp.gov.br","bauru.sp.gov.br","santos.sp.gov.br","ribeiraopreto.sp.gov.br","procon.sp.gov.br","cijun.sp.gov.br"],"org.br":["mobilize.org.br","redejuntos.org.br","transmundial.org.br","cebraspe.org.br","crcro.org.br","aasp.org.br","projetoguri.org.br","ivcbrasil.org.br","bioline.org.br","sbbd.org.br","britishcouncil.org.br","cenprotnacional.org.br","feliciorocho.org.br","tonarede.org.br","pcdob.org.br","sbpr.org.br","cria.org.br","sleepscience.org.br","amigbrasil.org.br","senairs.org.br"],"gov.br":["mj.gov.br","ebserh.gov.br","bcb.gov.br","brasil.gov.br","vlibras.gov.br","ibge.gov.br","dnit.gov.br","tesouro.gov.br","in.gov.br","presidencia.gov.br","inss.gov.br","icmbio.gov.br","itamaraty.gov.br","caixa.gov.br","depen.gov.br","epe.gov.br","anvisa.gov.br","serpro.gov.br","acesso.gov.br","www.gov.br"],"br":["ufpr.br","ufsc.br","scielo.br","espm.br","ufc.br","uepg.br","uff.br","ufscar.br","ufrgs.br","inpe.br","ufmg.br","fgv.br","unasp.br","usp.br","ufrr.br","unesp.br","uniceub.br","senai.br","ufrj.br","puc-rio.br"],"jus.br":["tjgo.jus.br","cnj.jus.br","tjsp.jus.br","tjsc.jus.br","trf3.jus.br","tjpr.jus.br","tjrn.jus.br","tjce.jus.br","jfrn.jus.br","cjf.jus.br","trf5.jus.br","tjmg.jus.br","tst.jus.br","tjms.jus.br","tjrr.jus.br","tjmt.jus.br","tjdft.jus.br","trf2.jus.br","tjrj.jus.br","trf1.jus.br"],"to.gov.br":["barra.to.gov.br","siga.to.gov.br","publicidade.to.gov.br","central.to.gov.br","portaldesistemas.to.gov.br","diariooficial.to.gov.br","sgd.to.gov.br","sefaz.to.gov.br","adapec.to.gov.br","transparencia2.to.gov.br","cge.to.gov.br","refis.to.gov.br","ati.to.gov.br","convenio.to.gov.br","secom.to.gov.br","gurupi.to.gov.br","palmas.to.gov.br","www.to.gov.br","doe.to.gov.br","transparencia.to.gov.br"],"net.br":["portalgov.net.br","gctelecomunicacoes.net.br","inter.net.br","portaldagestaoderiscos.net.br","amoremcristo.net.br","webtec.net.br","filmesporno.net.br","zoedigital.net.br","pornotorrent.net.br","links.net.br","worldbrasil.net.br","singularcdn.net.br","membros-sexocasual.net.br","mbadvocacia.net.br","tvonlinegratis.net.br","sexocasual.net.br","alubar.net.br","clicknews.net.br","selecao.net.br","clickspeed.net.br"],"edu.br":["faculdadesantateresa.edu.br","ifsc.edu.br","ifrn.edu.br","cruzeirodosuleducacional.edu.br","ifrs.edu.br","utfpr.edu.br","fcrs.edu.br","cruzeirodosul.edu.br","eniac.edu.br","uca.edu.br","saolucas.edu.br","faveni.edu.br","ufsj.edu.br","ifc-camboriu.edu.br","univasf.edu.br","ifsertao-pe.edu.br","ufvjm.edu.br","ifam.edu.br","unijui.edu.br","fael.edu.br"],"pa.gov.br":["semedmaraba.pa.gov.br","detran.pa.gov.br","mojuidoscampos.pa.gov.br","cosanpa.pa.gov.br","cmtucuma.pa.gov.br","bombeiros.pa.gov.br","camaradeportodemoz.pa.gov.br","policiacivil.pa.gov.br","seplad.pa.gov.br","semas.pa.gov.br","obidos.pa.gov.br","santarem.pa.gov.br","age.pa.gov.br","igeprev.pa.gov.br","barcarena.pa.gov.br","belem.pa.gov.br","sefa.pa.gov.br","conceicaodoaraguaia.pa.gov.br","ourilandia.pa.gov.br","sipros.pa.gov.br"],"mus.br":["letras.mus.br","maistocadas.mus.br","lives.mus.br","baixar.mus.br","amazan.mus.br","classicosdosclassicos.mus.br","trilhasonora.mus.br","lettify.mus.br","musicas.mus.br","gomusic.mus.br","onstage.mus.br","abet.mus.br","ubem.mus.br","letras-letra.mus.br","ilvolo.mus.br","musicasmaistocadas.mus.br","hangar.mus.br","mct.mus.br","violaomandriao.mus.br","musikcity.mus.br"],"blog.br":["ars.blog.br","sextou.blog.br","bandeiradois.blog.br","xvideos.blog.br","xxxvideo.blog.br","videosdesexoxxx.blog.br","patricinha.blog.br","pornobrasil.blog.br","flagras.blog.br","pornohd.blog.br","sexopornogay.blog.br","car.blog.br","gostosashd.blog.br","luis.blog.br","incesto.blog.br","julianaporcaro.blog.br","xvideos10.blog.br","mesquita.blog.br","xvideosporno.blog.br","xhamster.blog.br"],"art.br":["destaque.art.br","vex.art.br","alemao.art.br","soquadrinhos.art.br","duboc.art.br","salasaopaulo.art.br","osesp.art.br","barco.art.br","danteopoeta.art.br","ebac.art.br","select.art.br","rogeriopedro.art.br","animation.art.br","xvideos.art.br","axis.art.br","rl.art.br","visao.art.br","kaio.art.br","vermontex.art.br","inspirarte.art.br"],"tmp.br":["elav.tmp.br","exposec.tmp.br","homologa.tmp.br","novo.tmp.br","homolog.tmp.br","code.tmp.br","eventos.tmp.br","endereco.tmp.br"],"leg.br":["pi.leg.br","pa.leg.br","pr.leg.br","rj.leg.br","pe.leg.br","mt.leg.br","rs.leg.br","congressonacional.leg.br","camara.leg.br","senado.leg.br","go.leg.br","ce.leg.br","rr.leg.br","interlegis.leg.br","ap.leg.br","al.leg.br","rn.leg.br","to.leg.br","normas.leg.br","pb.leg.br"],"ap.gov.br":["portaldoservidor.ap.gov.br","portal.ap.gov.br","sigdoc.ap.gov.br","policiacivil.ap.gov.br","siapen.ap.gov.br","prodap.ap.gov.br","macapa.ap.gov.br","esic.ap.gov.br","cea.ap.gov.br","transparencia.ap.gov.br","sefaz.ap.gov.br","detran.ap.gov.br","siplag.ap.gov.br","imap.ap.gov.br","siop.ap.gov.br","folhagea.ap.gov.br","jucap.ap.gov.br","oiapoque.ap.gov.br","prodoc.ap.gov.br","sigeduc.ap.gov.br"],"sc.gov.br":["ciga.sc.gov.br","diariomunicipal.sc.gov.br","pmf.sc.gov.br","sef.sc.gov.br","alesc.sc.gov.br","cbm.sc.gov.br","enavirtual.sc.gov.br","pae.sc.gov.br","garopaba.sc.gov.br","detrannet.sc.gov.br","cmpomerode.sc.gov.br","acaps.sc.gov.br","saude.sc.gov.br","transparencia.sc.gov.br","cultura.sc.gov.br","pc.sc.gov.br","blumenau.sc.gov.br","sed.sc.gov.br","jaraguadosul.sc.gov.br","criciuma.sc.gov.br"],"pr.gov.br":["mcaa.pr.gov.br","empresafacil.pr.gov.br","guaraniacu.pr.gov.br","pibema.pr.gov.br","camaracatanduvas.pr.gov.br","expresso.pr.gov.br","seed.pr.gov.br","appsesa.pr.gov.br","curitiba.pr.gov.br","fazenda.pr.gov.br","boaspraticasods.pr.gov.br","cascavel.pr.gov.br","catanduvas.pr.gov.br","diaadia.pr.gov.br","celepar.pr.gov.br","detran.pr.gov.br","identidadedigital.pr.gov.br","siges.pr.gov.br","londrina.pr.gov.br","agricultura.pr.gov.br"],"am.gov.br":["crmv.am.gov.br","pmm.am.gov.br","ajuri.am.gov.br","amazonas.am.gov.br","delegaciainterativa.am.gov.br","aades.am.gov.br","portaldoservidor.am.gov.br","educacao.am.gov.br","hemoam.am.gov.br","cmm.am.gov.br","pm.am.gov.br","imprensaoficial.am.gov.br","sefaz.am.gov.br","manaus.am.gov.br","saude.am.gov.br","transparencia.am.gov.br","sicop.am.gov.br","seduc.am.gov.br","sigeam.am.gov.br","fapeam.am.gov.br"],"mg.gov.br":["luz.mg.gov.br","pjf.mg.gov.br","detran.mg.gov.br","camaracaxambu.mg.gov.br","contagem.mg.gov.br","japaraiba.mg.gov.br","policiamilitar.mg.gov.br","divinopolis.mg.gov.br","fha.mg.gov.br","educacao.mg.gov.br","meioambiente.mg.gov.br","fazenda.mg.gov.br","saude.mg.gov.br","ouropreto.mg.gov.br","cmc.mg.gov.br","isp.mg.gov.br","sids.mg.gov.br","pocofundo.mg.gov.br","conselheirolafaiete.mg.gov.br","bdmg.mg.gov.br"],"mil.br":["eb.mil.br","fab.mil.br","marinha.mil.br","mar.mil.br","aer.mil.br","decea.mil.br"],"adv.br":["adveritas.adv.br","karpat.adv.br","maximilianofernandes.adv.br","fabianasouza.adv.br","alanaargolo.adv.br","pontesfialhojunqueira.adv.br","cdiassales.adv.br","sandromendes.adv.br","janfellipe.adv.br","durazzomedeiros.adv.br","sergiomerola.adv.br","tostesdepaula.adv.br","curyemouresimao.adv.br","eduardopessoa.adv.br","concursos.adv.br","advocaciawg.adv.br","sad.adv.br","anacrim.adv.br","medeirosadvocacia.adv.br","dlb.adv.br"],"inf.br":["matelecom.inf.br","netmicro.inf.br","plugnet.inf.br","ecowd.inf.br","intelidata.inf.br","millenium.inf.br","jornalhoje.inf.br","ssw.inf.br","vanguarda.inf.br","modamasculina.inf.br","ais.inf.br","wtm.inf.br","kti.inf.br","abim.inf.br","monero.inf.br","sot.inf.br","revista.inf.br","iptu.inf.br","cgn.inf.br","src.inf.br"],"rj.gov.br":["fazenda.rj.gov.br","rioclaro.rj.gov.br","jucerja.rj.gov.br","funesbom.rj.gov.br","rio.rj.gov.br","marica.rj.gov.br","niteroi.rj.gov.br","sumidouro.rj.gov.br","defesacivil.rj.gov.br","www.rj.gov.br","patydoalferes.rj.gov.br","pmerj.rj.gov.br","alerj.rj.gov.br","vassouras.rj.gov.br","macae.rj.gov.br","duquedecaxias.rj.gov.br","servidor.rj.gov.br","detran.rj.gov.br","procon.rj.gov.br","mesquita.rj.gov.br"],"eng.br":["solare.eng.br","datageosis.eng.br","buratto.eng.br","alfaengenharia.eng.br","mc.eng.br","nxt.eng.br","ster.eng.br","amp.eng.br","politec.eng.br","grupoconstruserv.eng.br","elewatt.eng.br","valedosol.eng.br","solarengenharia.eng.br","ecoenergia.eng.br","engefor.eng.br","legasys.eng.br","sk.eng.br","rpm.eng.br","ciles.eng.br","phd.eng.br"],"etc.br":["supernatural.etc.br","aumanack.etc.br","hysteria.etc.br","cdm.etc.br","papeldeparede.etc.br","mercado.etc.br","comofazer.etc.br","xvideos.etc.br","homologacao.etc.br","temtudo.etc.br","mineiros.etc.br","femininas.etc.br","recados.etc.br"],"rs.gov.br":["svrs.rs.gov.br","xangrila.rs.gov.br","triunfo.rs.gov.br","detran.rs.gov.br","al.rs.gov.br","riogrande.rs.gov.br","portaldetransito.rs.gov.br","tfemib.rs.gov.br","www.rs.gov.br","fapergs.rs.gov.br","ivoti.rs.gov.br","saude.rs.gov.br","condor.rs.gov.br","taquari.rs.gov.br","ssp.rs.gov.br","daer.rs.gov.br","sefaz.rs.gov.br","camarabraga.rs.gov.br","tudofacil.rs.gov.br","inova.rs.gov.br"],"ba.gov.br":["sefaz.ba.gov.br","marau.ba.gov.br","itapebi.ba.gov.br","detran.ba.gov.br","pppeconcessoes.ba.gov.br","al.ba.gov.br","alba.ba.gov.br","legislabahia.ba.gov.br","juazeiro.ba.gov.br","tca.ba.gov.br","salvador.ba.gov.br","egba.ba.gov.br","caravelas.ba.gov.br","seibahia.ba.gov.br","api2.ba.gov.br","saude.ba.gov.br","servicos.ba.gov.br","irdeb.ba.gov.br","tremedal.ba.gov.br","caatiba.ba.gov.br"],"eti.br":["boente.eti.br","zago.eti.br","rodrigolira.eti.br","robsonnascimento.eti.br","helpdesk.eti.br","akira.eti.br","anisio.eti.br","softnew.eti.br","wsci.eti.br","3stecnologia.eti.br","jr.eti.br","mariz.eti.br","fs.eti.br","pascoal.eti.br","kinoshita.eti.br","henriqueramos.eti.br","esj.eti.br"],"tv.br":["redeclima.tv.br","agronews.tv.br","lineup.tv.br","plataforma.tv.br","canal4.tv.br","estaticos.tv.br","pornogratis.tv.br","super.tv.br","xvideos.tv.br","sinal.tv.br","defesa.tv.br","tvaberta.tv.br","espn.tv.br","bancodeseries.tv.br","watch.tv.br","videochat.tv.br","easy.tv.br","smartonline.tv.br","pupilo.tv.br","tamandua.tv.br"],"coop.br":["cel.coop.br","unimedportovelho.coop.br","paraibacooperativo.coop.br","castrolanda.coop.br","comigo.coop.br","cooper.coop.br","cooperativismodecredito.coop.br","eita.coop.br","novaalianca.coop.br","sicrediuniao.coop.br","unimed.coop.br","unimedcascavel.coop.br","unimedfesp.coop.br","unimedmineiros.coop.br","unimedsorocaba.coop.br","solis.coop.br","ailos.coop.br","paranacooperativo.coop.br","integra.coop.br","unimedgoiania.coop.br"],"mp.br":["mpf.mp.br","mpdft.mp.br","mppr.mp.br","mpu.mp.br","mpt.mp.br","mprj.mp.br","mpm.mp.br","mpba.mp.br","mpal.mp.br","mpmg.mp.br","mprs.mp.br","cnmp.mp.br","mpsp.mp.br","mprn.mp.br","mppi.mp.br","mpce.mp.br","mpma.mp.br","mpgo.mp.br","mpse.mp.br","mpms.mp.br"],"es.gov.br":["coronavirus.es.gov.br","geobases.es.gov.br","iuna.es.gov.br","www.es.gov.br","vitoria.es.gov.br","sefaz.es.gov.br","vilavelha.es.gov.br","linhares.es.gov.br","iema.es.gov.br","imigrantes.es.gov.br","cdn.es.gov.br","guarapari.es.gov.br","anchieta.es.gov.br","vacinaeconfia.es.gov.br","detran.es.gov.br","domingosmartins.es.gov.br","laranjadaterra.es.gov.br","transparencia.es.gov.br","sedu.es.gov.br","tce.es.gov.br"],"go.gov.br":["cristalina.go.gov.br","cultura.go.gov.br","goiania.go.gov.br","juventude.go.gov.br","bombeiros.go.gov.br","inaciolandia.go.gov.br","senadorcanedo.go.gov.br","camaraleopoldodebulhoes.go.gov.br","agenciacoradenoticias.go.gov.br","vaptvupt.go.gov.br","camarauruana.go.gov.br","cavalcante.go.gov.br","dgap.go.gov.br","administracao.go.gov.br","aparecida.go.gov.br","itarumaprevi.go.gov.br","portaldoempreendedorgoiano.go.gov.br","santoantoniodegoias.go.gov.br","detran.go.gov.br","demae.go.gov.br"],"ind.br":["valverde.ind.br","iso-sobressalentes.ind.br","sonos.ind.br","ecoflex.ind.br","ceramicaprogresso.ind.br","gralha-azul.ind.br","tattoo.ind.br","globalembalagens.ind.br","agroaves.ind.br","eletronika.ind.br","focoenergia.ind.br","djmoveis.ind.br","adb.ind.br","atlas.ind.br","vencetudo.ind.br","micromazza.ind.br","mymax.ind.br","lar.ind.br","rivelli.ind.br","cope.ind.br"],"ppg.br":["adtech.ppg.br","danielgalindo.ppg.br","zoe.ppg.br","emarket.ppg.br","publicita.ppg.br","comunicacao360.ppg.br","pointcomunicacao.ppg.br","galeria.ppg.br","amkt.ppg.br","brand.ppg.br","asterisco.ppg.br"],"pi.gov.br":["saojosedopiaui.pi.gov.br","saude.pi.gov.br","prefeiturasantacruzdosmilagres.pi.gov.br","www.pi.gov.br","acessoainformacao.pi.gov.br","santoantoniodelisboa.pi.gov.br","eouv.pi.gov.br","diariooficial.pi.gov.br","capitaogervasiooliveira.pi.gov.br","teresina.pi.gov.br","piaui2008.pi.gov.br","fapepi.pi.gov.br","transparencia.pi.gov.br","webmail.pi.gov.br","sisprev.pi.gov.br","detran.pi.gov.br","seplan.pi.gov.br","ati.pi.gov.br","floriano.pi.gov.br","sefaz.pi.gov.br"],"ma.gov.br":["sefaz.ma.gov.br","aplicacoes.ma.gov.br","candidomendes.ma.gov.br","al.ma.gov.br","tce.ma.gov.br","trabalhojovem.ma.gov.br","sinfra.ma.gov.br","portodoitaqui.ma.gov.br","igualdaderacial.ma.gov.br","aged.ma.gov.br","detran.ma.gov.br","imperatriz.ma.gov.br","educacao.ma.gov.br","emap.ma.gov.br","procon.ma.gov.br","portaldoservidor.ma.gov.br","seati.ma.gov.br","empresafacil.ma.gov.br","segep.ma.gov.br","centraldomaranhao.ma.gov.br"],"bio.br":["guimaraes.bio.br","ninha.bio.br","oceanus.bio.br","sbi.bio.br","laza.bio.br","arthropodacytogenetics.bio.br","peabiru.bio.br","link.bio.br","cema.bio.br","meulink.bio.br","energy.bio.br","professor.bio.br","ebras.bio.br","bioservice.bio.br","mol.bio.br","afh.bio.br","luciacangussu.bio.br"],"mt.gov.br":["indiavai.mt.gov.br","vilabeladasantissimatrindade.mt.gov.br","vilarica.mt.gov.br","sinfra.mt.gov.br","seplag.mt.gov.br","al.mt.gov.br","camaracuiaba.mt.gov.br","sorriso.mt.gov.br","tce.mt.gov.br","www.mt.gov.br","camaracba.mt.gov.br","altafloresta.mt.gov.br","detrannet.mt.gov.br","sesp.mt.gov.br","sad.mt.gov.br","mtprev.mt.gov.br","rondolandia.mt.gov.br","altotaquari.mt.gov.br","sefaz.mt.gov.br","controladoria.mt.gov.br"],"eco.br":["ecycle.eco.br","ecocine.eco.br","gifs.eco.br","meuscontoseroticos.eco.br","biosis.eco.br","navegart.eco.br","mw.eco.br","freecell.eco.br","ecolimpo.eco.br","etis.eco.br","fcsolar.eco.br","foton.eco.br","lider.eco.br","3tsolar.eco.br","yellow.eco.br","libertyenergia.eco.br","meioinfo.eco.br","lugares.eco.br","energytech.eco.br","sunpark.eco.br"],"srv.br":["caritas.srv.br","palestrante.srv.br","ece.srv.br","desentupidoraemsaopaulo.srv.br","gp.srv.br","sisprof.srv.br","ifractal.srv.br","mextrade.srv.br","mts.srv.br","desentupidora.srv.br","prymeconsultoria.srv.br","lives.srv.br","dinamo.srv.br","crm.srv.br","oito.srv.br","netnews.srv.br","socius.srv.br","valor.srv.br","cloudtec.srv.br","timbre.srv.br"],"tur.br":["pousadadacachoeira.tur.br","esferafacil.tur.br","escolhaviagens.tur.br","pisa.tur.br","travelclass.tur.br","bento.tur.br","altus.tur.br","fazendasanfrancisco.tur.br","riostar.tur.br","panoramas.tur.br","agile.tur.br","ivetur.tur.br","montesiao.tur.br","ferias.tur.br","hoteisepousadas.tur.br","hotelsaintpaul.tur.br","ibitipoca.tur.br","tabapuadospireneus.tur.br","vltour.tur.br","infinityturismo.tur.br"],"pe.gov.br":["educacao.pe.gov.br","petrolandia.pe.gov.br","petrolina.pe.gov.br","cabo.pe.gov.br","sad.pe.gov.br","secti.pe.gov.br","sei.pe.gov.br","jaboatao.pe.gov.br","seres.pe.gov.br","olinda.pe.gov.br","recife.pe.gov.br","saude.pe.gov.br","detran.pe.gov.br","portais.pe.gov.br","upe.pe.gov.br","biblioteca.pe.gov.br","sefaz.pe.gov.br","lafepe.pe.gov.br","alepe.pe.gov.br","araripina.pe.gov.br"],"def.br":["dpu.def.br","rs.def.br","pa.def.br","ba.def.br","sp.def.br","rn.def.br","rj.def.br","ms.def.br","pr.def.br","ce.def.br","pi.def.br","mg.def.br"],"psi.br":["concordia.psi.br","tdkom.psi.br","cangere.psi.br","bitcom.psi.br","webnet.psi.br","uptelecom.psi.br","dtel.psi.br","globalnet.psi.br","superip.psi.br","san.psi.br","conecta.psi.br","plugnet.psi.br","speedfiber.psi.br","supernet.psi.br","mnet-telecom.psi.br","maisnet.psi.br","startnet.psi.br"],"g12.br":["assuncao.g12.br","cp2.g12.br","maua.g12.br","csji.g12.br","dombarreto.g12.br","colegiocatarinense.g12.br","britishschool.g12.br","anglopp.g12.br","monteiro.g12.br","pingodegente.g12.br","crb.g12.br","zaccaria.g12.br","santacruz.g12.br","glorinha.g12.br","saintjohn.g12.br","escolaparque.g12.br","colegiometodista.g12.br","concordia.g12.br"],"jor.br":["forte.jor.br","f5.jor.br","dm.jor.br","araujo.jor.br","saibamais.jor.br","atosefatos.jor.br","integracao.jor.br","focus.jor.br","reporterunesp.jor.br","jr.jor.br","folhadosudoeste.jor.br","caiogottlieb.jor.br","blogdobarbosa.jor.br","plural.jor.br","rededenoticiaspr.jor.br","inova.jor.br","livre.jor.br","portalcomunitario.jor.br","aereo.jor.br","ijmp.jor.br"],"pro.br":["periodicorease.pro.br","lumpac.pro.br","sparkle.pro.br","youtrade.pro.br","cortesdecabelo.pro.br","radcore.pro.br","ppghsuerj.pro.br","christianspencer.pro.br","nilo.pro.br","inscricao.pro.br","paulorodrigues.pro.br","evandrooliveira.pro.br","lec.pro.br","igor.pro.br","gu.pro.br","vilarejo.pro.br","garcia.pro.br","75anosdecinema.pro.br","brasmar.pro.br","online.pro.br"],"rn.gov.br":["cmsga.rn.gov.br","macaiba.rn.gov.br","saopedro.rn.gov.br","serracaiada.rn.gov.br","saude.rn.gov.br","saofernando.rn.gov.br","al.rn.gov.br","transparencia.rn.gov.br","natal.rn.gov.br","detran.rn.gov.br","diariooficial.rn.gov.br","adcon.rn.gov.br","consig.rn.gov.br","sigeduc.rn.gov.br","joaocamara.rn.gov.br","saogoncalo.rn.gov.br","itep.rn.gov.br","fapern.rn.gov.br","idiarn.rn.gov.br","rodolfofernandes.rn.gov.br"],"ms.gov.br":["spdo.ms.gov.br","segov.ms.gov.br","corumba.ms.gov.br","capital.ms.gov.br","sad.ms.gov.br","portaldoservidor.ms.gov.br","webanalytics.ms.gov.br","agepen.ms.gov.br","meudetran.ms.gov.br","detran.ms.gov.br","fundesporte.ms.gov.br","sefaz.ms.gov.br","iprefsul.ms.gov.br","bombeiros.ms.gov.br","sejusp.ms.gov.br","www.ms.gov.br","semagro.ms.gov.br","camara.ms.gov.br","id.ms.gov.br","pm.ms.gov.br"],"ce.gov.br":["cearatransparente.ce.gov.br","seduc.ce.gov.br","aratuba.ce.gov.br","itaitinga.ce.gov.br","caninde.ce.gov.br","cmfor.ce.gov.br","aesp.ce.gov.br","cultura.ce.gov.br","detran.ce.gov.br","fortaleza.ce.gov.br","sps.ce.gov.br","delegaciaeletronica.ce.gov.br","etice.ce.gov.br","seplag.ce.gov.br","cge.ce.gov.br","esp.ce.gov.br","sobral.ce.gov.br","sct.ce.gov.br","saude.ce.gov.br","seinfra.ce.gov.br"],"vlog.br":["xvideo.vlog.br","pornocaseiro.vlog.br","xvideos.vlog.br","filmeporno.vlog.br","pornogratis.vlog.br","videosporno.vlog.br","xvidios.vlog.br","videoporno.vlog.br","videosdesexo.vlog.br","pornogay.vlog.br","pornobrasileiro.vlog.br","xvideoss.vlog.br","videospornogratis.vlog.br"],"fot.br":["andreianaomi.fot.br","precisodefotografo.fot.br","leandro.fot.br","kleber.fot.br","oliciopelosi.fot.br","saycheese.fot.br","ser.fot.br","marcomaia.fot.br","eduardorocha.fot.br"],"arq.br":["figueroa.arq.br","simoneprado.arq.br","cadblocos.arq.br","contemporanea.arq.br","phi.arq.br","amdecor.arq.br","hf.arq.br","loricrizel.arq.br","360arquitetura.arq.br","maisbrasilia.arq.br","set.arq.br","lauraboechat.arq.br","marinaaraujo.arq.br","jauregui.arq.br","03arquitetura.arq.br","suzuki.arq.br","nae.arq.br","fernandapqueiroz.arq.br","construir.arq.br","class.arq.br"],"al.gov.br":["maceio.al.gov.br","sei.al.gov.br","pm.al.gov.br","ipasealsaude.al.gov.br","palmeiradosindios.al.gov.br","ipaseal.al.gov.br","murici.al.gov.br","satuba.al.gov.br","atalaia.al.gov.br","delmirogouveia.al.gov.br","defesaagropecuaria.al.gov.br","saude.al.gov.br","transparencia.al.gov.br","sefaz.al.gov.br","riolargo.al.gov.br","gabinetecivil.al.gov.br","facilita.al.gov.br","alagoasdigital.al.gov.br","seplag.al.gov.br","juceal.al.gov.br"],"med.br":["beatrizbotelho.med.br","babycenter.med.br","bulas.med.br","abc.med.br","ortopediaonline.med.br","panacea.med.br","multiscan.med.br","catalogo.med.br","coris.med.br","neovita.med.br","clinicadopulmao.med.br","diabetes.med.br","pro-bs.med.br","site.med.br","icca.med.br","cbms.med.br","clinicaortotrauma.med.br","atend.med.br","digest.med.br","nu.med.br"],"pb.gov.br":["detran.pb.gov.br","prata.pb.gov.br","camaraibiara.pb.gov.br","malta.pb.gov.br","transparencia.pb.gov.br","lagoadedentro.pb.gov.br","der.pb.gov.br","cajazeiras.pb.gov.br","suplan.pb.gov.br","pm.pb.gov.br","seliganoenem.pb.gov.br","pedroregis.pb.gov.br","tce.pb.gov.br","camarataperoa.pb.gov.br","joaopessoa.pb.gov.br","wsdetran.pb.gov.br","santahelena.pb.gov.br","bombeiros.pb.gov.br","saobento.pb.gov.br","campinagrande.pb.gov.br"],"adm.br":["destake.adm.br","gestaoonline.adm.br","almeida.adm.br","diamond.adm.br","sato.adm.br","cra-rj.adm.br","house.adm.br","novi.adm.br","gepam.adm.br","apioneira.adm.br","gruposaojose.adm.br","gross.adm.br","jarvis.adm.br","grupoempresarial.adm.br","empowerment.adm.br","webstudio.adm.br","webcard.adm.br"],"se.gov.br":["detran.se.gov.br","aracaju.se.gov.br","transparenciasergipe.se.gov.br","sindec.se.gov.br","www.se.gov.br","expresso.se.gov.br","nossasenhoradasdores.se.gov.br","seduc.se.gov.br","ssp.se.gov.br","funesa.se.gov.br","camaradesantoamaro.se.gov.br","emgetis.se.gov.br","santaluziadoitanhi.se.gov.br","camarasantarosadelima.se.gov.br","boquim.se.gov.br","seplag.se.gov.br"],"imb.br":["indice.imb.br","vasselai.imb.br","mantiqueiraimoveis.imb.br","campinas.imb.br","activa.imb.br","souzaimoveis.imb.br","douglasimoveis.imb.br","junia.imb.br","seucorretor.imb.br","jrimoveis.imb.br","orlandosilva.imb.br","pimentelimoveis.imb.br","engeotec.imb.br","solnascente.imb.br","mariazilda.imb.br","nobreimoveis.imb.br","cidadeimoveis.imb.br","rossiimoveis.imb.br","premiereimoveis.imb.br","villageimobiliaria.imb.br"],"fm.br":["radio97.fm.br","sintonia.fm.br","96fm.fm.br","studio.fm.br","band.fm.br","vanguarda.fm.br","virtual.fm.br","popular.fm.br","tupa.fm.br","clubeum.fm.br","sol.fm.br","progresso.fm.br","imperial.fm.br","cabobranco.fm.br","gospel.fm.br","radionovaindependencia.fm.br","radioviva.fm.br","educadora.fm.br","liriosdocampo.fm.br","radiorainha.fm.br"],"rr.gov.br":["saude.rr.gov.br","boavista.rr.gov.br","bombeiros.rr.gov.br","sejuc.rr.gov.br","sefaz.rr.gov.br","transparencia.rr.gov.br","governodigital.rr.gov.br","portal.rr.gov.br","detran.rr.gov.br","altoalegre.rr.gov.br","www.rr.gov.br","mpc.rr.gov.br","uiramuta.rr.gov.br"],"am.br":["educadora.am.br","portofeliz.am.br","rc.am.br","radiocapinzal.am.br","colmeia.am.br","progresso.am.br","radioriodejaneiro.am.br","radiomensagem.am.br","radiolider.am.br"],"ro.gov.br":["emater.ro.gov.br","portovelho.ro.gov.br","transparencia.ro.gov.br","pm.ro.gov.br","itapuadooeste.ro.gov.br","chupinguaia.ro.gov.br","vilhena.ro.gov.br","sesau.ro.gov.br","camaradeitapuadooeste.ro.gov.br","idaron.ro.gov.br","sistemas.ro.gov.br","tce.ro.gov.br","pc.ro.gov.br","detran.ro.gov.br","sefin.ro.gov.br","rondonia.ro.gov.br","pimentabueno.ro.gov.br","seduc.ro.gov.br","detic.ro.gov.br","sejus.ro.gov.br"],"trd.br":["sbj.trd.br","multitude.trd.br","fernandabotta.trd.br"],"ntr.br":["nutriflex.ntr.br","site.ntr.br"],"esp.br":["aabrbauru.esp.br","cefit.esp.br","golfe.esp.br","fmo.esp.br","skate.esp.br","fgf.esp.br","ecoesporte.esp.br","planetabola.esp.br","superliga.esp.br","instituto.esp.br","abp.esp.br","cbpm.esp.br","gpa.esp.br","allfit.esp.br","st.esp.br","superar.esp.br","smarttennis.esp.br","brasileirodeenduro.esp.br","crb.esp.br","ik.esp.br"],"radio.br":["player.radio.br","play.radio.br","radiocoracaofiel.radio.br","sintonizar.radio.br","uniaofm.radio.br","centraldenoticias.radio.br","dimagem.radio.br","sistema.radio.br","youngtech.radio.br","93fm.radio.br","website.radio.br","social.radio.br","planetahits.radio.br","meninafm.radio.br","fortalezafm.radio.br","ouvir.radio.br"],"cim.br":["mazzola.cim.br","fa.cim.br","imoveisx.cim.br","brognoli.cim.br","ramonjmedeiros.cim.br","andersonmiranda.cim.br","tome.cim.br","grupo.cim.br","amazon.cim.br"],"rec.br":["santamonica.rec.br","pcr.rec.br","avi.rec.br","toledao.rec.br","artemis.rec.br","educ.rec.br","estalo.rec.br","alpha.rec.br","bot.rec.br","marcozero.rec.br"],"tc.br":["tcerj.tc.br","tcmgo.tc.br","tcesc.tc.br","tceto.tc.br","tcees.tc.br","tcero.tc.br"],"cnt.br":["crn.cnt.br","sertec.cnt.br","contabilidadedominio.cnt.br","maiscontrole.cnt.br","servicont.cnt.br","contadores.cnt.br","certus.cnt.br","numerabilis.cnt.br","atos.cnt.br","capitalsocial.cnt.br","contar.cnt.br","valdecicontabilidade.cnt.br","pioneira.cnt.br","mercurio.cnt.br","deltec.cnt.br","missoes.cnt.br"],"psc.br":["anaclaudia.psc.br","psicorj.psc.br","alinecosta.psc.br","iths.psc.br","corpo-mente.psc.br","igt.psc.br","oswrod.psc.br","psicosignificar.psc.br","abrangente.psc.br","suzanyribeiro.psc.br"],"ac.gov.br":["imagens.ac.gov.br","licitacao.ac.gov.br","agencia.ac.gov.br","tce.ac.gov.br","tarauaca.ac.gov.br","sefaznet.ac.gov.br","transparencia.ac.gov.br","gep.ac.gov.br","cruzeirodosul.ac.gov.br","riobranco.ac.gov.br","aldeiafm.ac.gov.br","imc.ac.gov.br","diario.ac.gov.br","detran.ac.gov.br","webmail.ac.gov.br"],"bsb.br":["hospitaldaplastica.bsb.br","selfstorage.bsb.br","tecnicatupler.bsb.br","cdrdf.bsb.br","toldosdf.bsb.br","otorrinobrasiliadf.bsb.br","oespecialista.bsb.br","psicologia.bsb.br","aguasclarasvegan.bsb.br","startprint.bsb.br","siqueiraimoveis.bsb.br","jac.bsb.br","administradoracondominio.bsb.br","institutovencer.bsb.br","abrirempresa.bsb.br","alfahospitalar.bsb.br"],"agr.br":["integra.agr.br","finpec.agr.br","cedro.agr.br","agroexport.agr.br","ibl.agr.br","agrocp.agr.br","agroprojeto.agr.br","sna.agr.br","ipb.agr.br","alvo.agr.br","agrinvest.agr.br","sempre.agr.br","base.agr.br","greentree.agr.br","seara.agr.br","amabrasil.agr.br","grupogerar.agr.br","agrorosa.agr.br","tecseed.agr.br","aguia.agr.br"],"natal.br":["humanasaude.natal.br","brincarnoquintal.natal.br","conheca.natal.br","greenpoint.natal.br"],"poa.br":["prefeitura.poa.br","curvados.poa.br","cidadealta.poa.br","rmaissaude.poa.br","superoferta.poa.br","copospersonalizados.poa.br","tudonoticia.poa.br","farmaciademanipulacao.poa.br","prosperi.poa.br"],"odo.br":["olsen.odo.br","miriambaldin.odo.br","grupo.odo.br","fernandoramos.odo.br","maccarini.odo.br","marciakanashiro.odo.br","zeppiniodonto.odo.br","implantededentes.odo.br","dentcare.odo.br","smiledesign.odo.br","odontologicoamil.odo.br","ortodontia.odo.br","coimplante.odo.br","felipeporto.odo.br","oralsul.odo.br"],"flog.br":["hentaibrasil.flog.br","hentai.flog.br","futebol.flog.br","coroas.flog.br","desentupidora.flog.br","carros2022.flog.br","xvideos.flog.br","contoseroticos.flog.br","saudeebemestar.flog.br"],"rio.br":["lojabotafogo.rio.br","meuip.rio.br","shoppingboulevard.rio.br","lig.rio.br","guiadailha.rio.br","robot.rio.br","cleanenergy.rio.br","zazacafe.rio.br","lopes.rio.br","ayla.rio.br","arraial.rio.br","nb.rio.br","genial.rio.br","hospitaisdecampanha.rio.br","eteot.rio.br"],"qsl.br":["py1geb.qsl.br","crafi.qsl.br","py2bbs.qsl.br","813am.qsl.br","py.qsl.br","rst.qsl.br"],"wiki.br":["arquivo.wiki.br","registrodedominio.wiki.br","latinoamericana.wiki.br","pabxvirtual.wiki.br","botanicaamazonica.wiki.br","animaarpg.wiki.br","news.wiki.br","memes.wiki.br","google.wiki.br","hospedagemdesites.wiki.br"],"vet.br":["clubeanimal.vet.br","suprimed.vet.br","simples.vet.br","indubras.vet.br","unopet.vet.br","laborvet.vet.br","facilita.vet.br","sou.vet.br","vetminds.vet.br","bulario.vet.br","pastoralemao.vet.br","crisa.vet.br","doctor.vet.br","petspa.vet.br"],"app.br":["polen.app.br","musicadacidade.app.br","jaentrego.app.br","lkp.app.br","multibuscas.app.br","usemarrie.app.br","omne.app.br","usemob.app.br","nogafoods.app.br","nextlevel.app.br","oliva.app.br","placasdevideo.app.br","menudigital.app.br","consultas71035607140.app.br","app4you.app.br","alugueltemporada.app.br","hotmail.app.br","publibox.app.br","superzap.app.br","gomenu.app.br"],"b.br":["banpara.b.br","bradesconetempresa.b.br","campanhasnext.b.br","banestes.b.br","itau.b.br","caixa.b.br","nxtapp.b.br","bip.b.br","paranabanco.b.br","bradesco.b.br"],"curitiba.br":["multipecas.curitiba.br","portoeseletronicos.curitiba.br","utfpr.curitiba.br","criacaodewebsite.curitiba.br","amo.curitiba.br","andrologia.curitiba.br","mascote.curitiba.br","desentupidorateleesgoto.curitiba.br","periciadeengenharia.curitiba.br","iphco-ifpr.curitiba.br","xiaomi.curitiba.br","peixaria.curitiba.br"],"log.br":["iconex.log.br","novavida.log.br","perlog.log.br"],"fortal.br":["corretoremfortaleza.fortal.br"],"dev.br":["scuba.dev.br","adi.dev.br","wicode.dev.br","lkp.dev.br","actuseducacional.dev.br","iam.dev.br","feliperamos.dev.br","mms.dev.br","webtech.dev.br","rsk.dev.br","paralax.dev.br","dphsystem.dev.br","bruno.dev.br","hashiracode.dev.br","olsen.dev.br","ecofy.dev.br","sakurai.dev.br","game.dev.br"],"mat.br":["site.mat.br","primos.mat.br","igm.mat.br","tia.mat.br","professorwaltertadeu.mat.br","opm.mat.br","oliveira.mat.br","im-uff.mat.br","rodrigodevolder.mat.br","calex.mat.br","conrado.mat.br","valorx.mat.br","oda.mat.br"],"lel.br":["moedaeselo.lel.br","anaclaraleiloes.lel.br","leiloeiros.lel.br","fernandaleiloes.lel.br","philatelia.lel.br","acervobrasil.lel.br","leiloeiro.lel.br","antonioferreira.lel.br","bertoncello.lel.br","jorgebrasil.lel.br","emporiocentralantiguidades.lel.br","bahialeiloes.lel.br"],"maringa.br":["descubra.maringa.br","cdd.maringa.br"],"maceio.br":["apartamentospraiafrances.maceio.br"],"vix.br":["vitoriacortinas.vix.br","sb.vix.br","nxt.vix.br","casadoiphone.vix.br","srmustache.vix.br"],"slg.br":["entropia.slg.br"],"joinville.br":["icebi2019.joinville.br","grafica.joinville.br","bobsom.joinville.br","npee.joinville.br"],"londrina.br":["ceal.londrina.br"],"far.br":["cannabisfarma.far.br","homefarma.far.br","ophtalmed.far.br","singularis.far.br","fbf.far.br","assistenciafarmaceutica.far.br","newfarma.far.br","ismed.far.br","videbula.far.br"],"emp.br":["moveis.emp.br","regal.emp.br","mover.emp.br","construtora.emp.br","anderson.emp.br","florenca.emp.br","eletrowatts.emp.br","sorocaba.emp.br","vidracaria.emp.br","renove.emp.br","google.emp.br","seo.emp.br"],"bhz.br":["centrovet.bhz.br","saindobem.bhz.br","pcem.bhz.br","sjbrstd.bhz.br","redesign.bhz.br","viajarhoje.bhz.br","youtube.bhz.br","aqui.bhz.br"],"sampa.br":["lojadoprazer.sampa.br","apcr.sampa.br","s2.sampa.br","samuel.sampa.br","autofix.sampa.br","mastermind.sampa.br"],"ribeirao.br":["medicina.ribeirao.br"],"seg.br":["sen.seg.br","servidor.seg.br","gullfoss-isl.seg.br","limpanomebrasil.seg.br","fe.seg.br","invi.seg.br","cscorretora.seg.br"],"jampa.br":["anezioaraujo.jampa.br"],"slz.br":["tradedigital.slz.br","colegiosantafe.slz.br","camara.slz.br","horaextra.slz.br"],"gru.br":["gibamoveis.gru.br","guia.gru.br","google.gru.br","aliancaimoveis.gru.br"],"ong.br":["brilhonoolhar.ong.br","projetocontacomigo.ong.br","carapavivo.ong.br","centralsantaines.ong.br","institutoleucena.ong.br","mdpf.ong.br","somosmais.ong.br","scorealto.ong.br","abraceesperanca.ong.br","amigosdoverde.ong.br","institutoadonai.ong.br","projetoprospera.ong.br","himalaya.ong.br"],"salvador.br":["condominiomondial.salvador.br","sindicoprofissional.salvador.br"],"tec.br":["smartcity.tec.br","genesis.tec.br","avaliacoes.tec.br","resolve.tec.br","nre.tec.br","concentre.tec.br","gasup.tec.br","quark.tec.br","homelucrativo.tec.br","vlink.tec.br","smartcompany.tec.br","eshop.tec.br","zello.tec.br","3daweb.tec.br","diretiva.tec.br"],"teo.br":["eventospucrio.teo.br"],"sjc.br":["pradosolucoes.sjc.br","montadordemoveis.sjc.br"],"anani.br":["server.anani.br"],"belem.br":["imoveisbelem.belem.br","griffo.belem.br","olivertemper.belem.br"],"riopreto.br":["costureira.riopreto.br"],"bmd.br":["biomedicinaestetica.bmd.br","anacarolina.bmd.br"],"fnd.br":["assumpcao.fnd.br"],"enf.br":["angelcare.enf.br"],"coz.br":["foodies.coz.br"],"barueri.br":["solange.barueri.br"],"sorocaba.br":["psicologo.sorocaba.br","cortinas.sorocaba.br","clinicadeolhos.sorocaba.br"],"recife.br":["securitycenter.recife.br","visit.recife.br","enjoy.recife.br"],"udi.br":["mega.udi.br","camerasdeseguranca.udi.br"],"caxias.br":["sidart.caxias.br","leparc.caxias.br"],"abc.br":["digital.abc.br","mac.abc.br","capsulasecursos.abc.br","google.abc.br"],"campinas.br":["rjb.campinas.br","arcondicionadoautomotivo.campinas.br","google.campinas.br"],"not.br":["8tabelionato.not.br","cartoriooliveiramedeiros.not.br"],"ecn.br":["sebh.ecn.br"],"aju.br":["mendonca.aju.br"],"osasco.br":["ouvidoriadolegislativo.osasco.br"],"goiania.br":["agenciadesite.goiania.br"],"floripa.br":["3wceh2019.floripa.br"]},"type":"cctld","isIDN":false,"rdapServers":["https://rdap.registro.br/domain/"],"rdapUpdated":1641149386360}