{"tld":"dating","tldUpdated":1586995200000,"tldCreated":1390435200000,"whoisServer":["whois.nic.dating"],"registry":"http://www.donuts.domains/","ianaUrl":"https://www.iana.org/domains/root/db/dating.html","t":1616648275661,"version":1,"sampleDomains":{"dating":["teaser.dating","marriedbutlooking.dating","naughtysecret.dating","successful.dating","intrigue.dating","pure.dating","wonder.dating","datehookup.dating","dmc.dating","olo.dating","matures.dating","easyflirt.dating","secret.dating","static.dating","lov.dating","farmersonly.dating","fwb.dating","ruby.dating","silver-fox.dating","gayfriendly.dating"]},"type":"generic","isIDN":false,"rdapServers":["https://rdap.donuts.co/rdap/domain/"],"rdapUpdated":1616650391185}