{"tld":"dentist","tldUpdated":1626134400000,"tldCreated":1400716800000,"whoisServer":["whois.nic.dentist"],"registry":"http://www.donuts.domains/","ianaUrl":"https://www.iana.org/domains/root/db/dentist.html","t":1630847786767,"version":1,"sampleDomains":{"dentist":["antigonish.dentist","implantsguru.dentist","newportnewsva.dentist","eurokappa.dentist","greenvillesc.dentist","santarosacosmetic.dentist","overlandparkks.dentist","schenectadypediatric.dentist","sunnyvalefamilysmiles.dentist","carolstreamil.dentist","booking.dentist","thenew.dentist","adarsh.dentist","drspierer.dentist","b4230.dentist","fortoothhurty.dentist","dentalarts.dentist","dentalclinictoronto.dentist","belle32.dentist","nearme.dentist"]},"type":"generic","isIDN":false,"rdapServers":["https://rdap.donuts.co/rdap/domain/"],"rdapUpdated":1630860995359}