{"tld":"express","tldUpdated":1626739200000,"tldCreated":1426118400000,"whoisServer":["whois.nic.express"],"registry":"http://www.donuts.domains/","ianaUrl":"https://www.iana.org/domains/root/db/express.html","t":1635164430763,"version":1,"sampleDomains":{"express":["torrent.express","aftermarket.express","public.express","static.express","ti.express","filmyzilla.express","zarin.express","stork.express","dnepr.express","mediaserver.express","petfood.express","bluecare.express","business.express","doit.express","xi.express","pdfjs.express","narkolog.express","mrbit.express","shemale.express","9xmovies.express"]},"type":"generic","isIDN":false,"rdapServers":["https://rdap.donuts.co/rdap/domain/"],"rdapUpdated":1635167449109}