{"tld":"faith","tldUpdated":1658361600000,"tldCreated":1423094400000,"whoisServer":["whois.nic.faith"],"registry":"http://nic.faith","ianaUrl":"https://www.iana.org/domains/root/db/faith.html","t":1672688667925,"version":1,"sampleDomains":{"faith":["bestcultureworld.faith","beeg.faith","judea.faith","go4th.faith","pein.faith","myemotion.faith","marvelvsdc.faith","fabnews.faith","marvelcomics.faith","backforgood.faith","myccp.faith","centerpoint.faith","albanychurch.faith","lain.faith","bol.faith","immanuelucc.faith","egybest.faith","swaminarayan.faith","ye24.faith","faraz.faith"]},"type":"generic","isIDN":false,"rdapServers":["https://rdap.nic.faith/domain/"],"rdapUpdated":1658865630701}