{"tld":"fashion","tldUpdated":1692057600000,"tldCreated":1414022400000,"whoisServer":["whois.nic.fashion"],"registry":"http://nic.fashion/","ianaUrl":"https://www.iana.org/domains/root/db/fashion.html","t":1692609910477,"version":1,"sampleDomains":{"fashion":["marah.fashion","alinacernatescu.fashion","seek.fashion","pickup.fashion","dazz.fashion","redwood.fashion","gaat.fashion","uyleesboutique.fashion","codes.fashion","find.fashion","femuse.fashion","symbol.fashion","haal.fashion","seduction.fashion","urstyle.fashion","theindustry.fashion","mayfaircollection.fashion","ortho.fashion","icreate.fashion","stonerose.fashion"]},"type":"generic","isIDN":false,"rdapServers":["https://rdap.nic.fashion/domain/"],"rdapUpdated":1658865631761}