{"tld":"foundation","tldUpdated":1587081600000,"tldCreated":1391644800000,"whoisServer":["whois.nic.foundation"],"registry":"http://www.donuts.domains/","ianaUrl":"https://www.iana.org/domains/root/db/foundation.html","t":1614319084126,"version":1,"sampleDomains":{"foundation":["peterlindbergh.foundation","thompsonfamily.foundation","icon.foundation","ravencoin.foundation","batyr.foundation","mobilecoin.foundation","taak.foundation","identity.foundation","algorand.foundation","0608.foundation","swap.foundation","kloranebotanical.foundation","pxn.foundation","techdreams.foundation","fantom.foundation","weloveanimals.foundation","certik.foundation","get.foundation","lgbt.foundation","coko.foundation"]},"type":"generic","isIDN":false,"rdapServers":["https://rdap.donuts.co/rdap/domain/"],"rdapUpdated":1614322062131}