{"tld":"holiday","tldUpdated":1694476800000,"tldCreated":1387411200000,"whoisServer":["whois.nic.holiday"],"registry":"https://www.identity.digital/","ianaUrl":"https://www.iana.org/domains/root/db/holiday.html","t":1745434466860,"version":1,"sampleDomains":{"holiday":["tourdumontblanc.holiday","lankan.holiday","munnar.holiday","haveagood.holiday","easybooking.holiday","exclusivetravel.holiday","salut.holiday","gay2022.holiday","checklist.holiday","imperial.holiday","safar.holiday","dayofthedead.holiday","matrix.holiday","familiving.holiday","ufabet.holiday","domsod.holiday","causewaycoast.holiday","orlandohotelfinder.holiday","9xmovies.holiday","7starhd.holiday","ihlasarmutlu.holiday","itsyour.holiday","najm.holiday","cyprusairways.holiday","travelpedia.holiday","bitcoin.holiday","vibrant.holiday","suicide.holiday","travclan.holiday","booksunday.holiday","yolo.holiday","images.holiday","666.holiday","whatabout.holiday","starry.holiday","7.holiday","nic.holiday"]},"type":"generic","isIDN":false,"rdapServers":["https://rdap.donuts.co/rdap/domain/"],"rdapUpdated":1658865667336}