{"tld":"love","tldUpdated":1586995200000,"tldCreated":1427241600000,"whoisServer":["whois.nic.love"],"registry":"http://get.love","ianaUrl":"https://www.iana.org/domains/root/db/love.html","t":1630848033627,"version":1,"sampleDomains":{"love":["kinokordon.love","herhers.love","stray.love","123moviesfree.love","pornolomka.love","youjo.love","stepdaughter.love","anwap.love","bigboss.love","tukif.love","rusex.love","ketab.love","saber.love","masked.love","galactic.love","vsegda.love","igra.love","91porn.love","forced.love","prostitutki-24.love"]},"type":"generic","isIDN":false,"rdapServers":["https://rdap.centralnic.com/love/domain/"],"rdapUpdated":1630861089861}