{"tld":"ltd","tldUpdated":1636502400000,"tldCreated":1438819200000,"whoisServer":["whois.nic.ltd"],"registry":"http://www.donuts.domains/","ianaUrl":"https://www.iana.org/domains/root/db/ltd.html","t":1651163291807,"version":1,"sampleDomains":{"ltd":["workcoin.ltd","amd.ltd","ouyicn.ltd","geeks.ltd","egybest.ltd","downloadhub.ltd","cryptofxtrade.ltd","chmod777.ltd","geeko.ltd","myfood.ltd","utahcapitalfx.ltd","123moviesfree.ltd","coinall.ltd","0123movies.ltd","gpm.ltd","notifications.ltd","xmcp.ltd","bestweb.ltd","lordfilm.ltd","koran.ltd"]},"type":"generic","isIDN":false,"rdapServers":["https://rdap.donuts.co/rdap/domain/"],"rdapUpdated":1652312350367}