{"tld":"mg","tldUpdated":1564963200000,"tldCreated":806630400000,"whoisServer":["whois.nic.mg"],"registry":"http://www.nic.mg","ianaUrl":"https://www.iana.org/domains/root/db/mg.html","t":1651163314389,"version":1,"sampleDomains":{"mg":["e-tady.mg","edbm.mg","jirama.mg","yts.mg","orangemail.mg","hyundai.mg","chronos.mg","educassist.mg","univ-antananarivo.mg","sirr.mg","ambatovy.mg","bet261.mg","supermarche.mg","google.mg","cosmos.mg","oa.mg","nite.mg","laplume.mg","storm.mg","upmedia.mg"],"gov.mg":["primature.gov.mg","sante.gov.mg","vakisiny.gov.mg","defense.gov.mg","mef.gov.mg","cnlegis.gov.mg","gendarmerie.gov.mg","mfb.gov.mg","mndpt.gov.mg","education.gov.mg","recherches.gov.mg","mesupres.gov.mg","metfp.gov.mg","digital.gov.mg","csi.gov.mg","resiliencemada.gov.mg","diplomatie.gov.mg","mefb.gov.mg","pn.gov.mg","mjs.gov.mg"],"edu.mg":["univ-antsiranana.edu.mg","mesupres.edu.mg","univ-mahajanga.edu.mg","irenala.edu.mg","ist-ambositra.edu.mg","cnrit.edu.mg","zurcher.edu.mg"],"com.mg":["shoprite.com.mg","nikon.com.mg","roblox.com.mg","dhl.com.mg","amazon.com.mg"],"co.mg":["demo.co.mg"],"org.mg":["enmg.org.mg","mariestopes.org.mg"]},"type":"cctld","isIDN":false,"rdapServers":[],"rdapUpdated":1655259420400}