{"tld":"paris","tldUpdated":1637625600000,"tldCreated":1395878400000,"whoisServer":["whois.nic.paris"],"registry":"http://mondomaine.paris.fr/","ianaUrl":"https://www.iana.org/domains/root/db/paris.html","t":1651163400077,"version":1,"sampleDomains":{"paris":["aventique.paris","woo.paris","dna.paris","yay.paris","osteopathes.paris","bonjour.paris","lesconstructionsmodernes.paris","restaurant-lassiette.paris","fhcm.paris","tiemo.paris","femmefatale.paris","cloud-services.paris","institut-kinesitherapie.paris","mondial.paris","lpsm.paris","arnaudnicolas.paris","la-scene.paris","elbe.paris","tkt.paris","p2p.paris"]},"type":"generic","isIDN":false,"rdapServers":["https://rdap.nic.paris/domain/"],"rdapUpdated":1651163950618}