{"tld":"pf","tldUpdated":1603756800000,"tldCreated":827193600000,"whoisServer":["whois.registry.pf"],"registry":false,"ianaUrl":"https://www.iana.org/domains/root/db/pf.html","t":1646658792900,"version":1,"sampleDomains":{"pf":["annuaireopt.pf","tahitiheritage.pf","osb.pf","tntv.pf","upf.pf","zuckoo.pf","gov.pf","google.pf","polymeubles.pf","etis.pf","cloud.pf","education.pf","isi.pf","radio1.pf","americanexpress.pf","petites-annonces.pf","monvr.pf","edt.pf","vini.pf","ora.pf"]},"type":"cctld","isIDN":false,"rdapServers":[],"rdapUpdated":1646659417563}