{"tld":"photo","tldUpdated":1604534400000,"tldCreated":1389830400000,"whoisServer":["whois.uniregistry.net","whois.nic.photo"],"registry":"http://uniregistry.link","ianaUrl":"https://www.iana.org/domains/root/db/photo.html","t":1637869932797,"version":1,"sampleDomains":{"photo":["udo.photo","hoop.photo","voyages.photo","ishoot.photo","dekiteru.photo","snaps.photo","shoot.photo","ronski.photo","streetart.photo","khayyam.photo","alib.photo","reza.photo","ixbt.photo","7starhd.photo","gallery.photo","sliv.photo","zvezda.photo","9kmovies.photo","beckhamdigital.photo","altadefinizione01.photo"]},"type":"generic","isIDN":false,"rdapServers":["https://whois.uniregistry.net/rdap/domain/"],"rdapUpdated":1637870476933}