{"tld":"pictures","tldUpdated":1635292800000,"tldCreated":1396483200000,"whoisServer":["whois.nic.pictures"],"registry":"http://www.donuts.domains/","ianaUrl":"https://www.iana.org/domains/root/db/pictures.html","t":1641148934179,"version":1,"sampleDomains":{"pictures":["supermodel.pictures","ib.pictures","nakedgirls.pictures","russianporn.pictures","hd4free.pictures","investorportal.pictures","cnft.pictures","maturesex.pictures","djdan.pictures","cleanup.pictures","nordic.pictures","pornhoarder.pictures","gauvin.pictures","site.pictures","nakedteen.pictures","checkmy.pictures","imguur.pictures","jav.pictures","mypussy.pictures","mytits.pictures"]},"type":"generic","isIDN":false,"rdapServers":["https://rdap.donuts.co/rdap/domain/"],"rdapUpdated":1641149564510}