{"tld":"re","tldUpdated":1650585600000,"tldCreated":860371200000,"whoisServer":["whois.nic.re"],"registry":"http://www.nic.re/","ianaUrl":"https://www.iana.org/domains/root/db/re.html","t":1651163447690,"version":1,"sampleDomains":{"re":["oxtorrent.re","antenne.re","spark.re","katmoviehd.re","wait.re","pixiv.re","eztv.re","btnull.re","french-stream.re","codefi.re","yls.re","divxtotal.re","hdrezka.re","journal.re","toutela.re","javtorrent.re","linkco.re","adsco.re","yande.re","911.re"]},"type":"cctld","isIDN":false,"rdapServers":[],"rdapUpdated":1651163965365}