{"tld":"review","tldUpdated":1602460800000,"tldCreated":1423094400000,"whoisServer":["whois.nic.review"],"registry":"http://nic.review","ianaUrl":"https://www.iana.org/domains/root/db/review.html","t":1614319625939,"version":1,"sampleDomains":{"review":["chinavpn.review","newtab.review","newautoinsurance.review","tweowhvrim.review","mrbit.review","hookupsites.review","123movies.review","avto.review","dayta.review","zeroturnmowers.review","top10antivirus.review","dapp.review","luxubu.review","ghosthis.review","laptop.review","color.review","tesites.review","cartasdeamor.review","gaobook.review","amp.review"]},"type":"generic","isIDN":false,"rdapServers":["https://rdap.nic.review/domain/"],"rdapUpdated":1614322433820}