{"tld":"rugby","tldUpdated":1623888000000,"tldCreated":1490227200000,"whoisServer":["whois.nic.rugby"],"registry":"https://nic.rugby/","ianaUrl":"https://www.iana.org/domains/root/db/rugby.html","t":1630848204614,"version":1,"sampleDomains":{"rugby":["blues.rugby","rapid.rugby","pro14.rugby","newzealand.rugby","provincial.rugby","all.rugby","australia.rugby","springboks.rugby","thexv.rugby","wallabies.rugby","qld.rugby","france2023.rugby","rugbyatl.rugby","majorleague.rugby","sa.rugby","vic.rugby","world.rugby","women.rugby","usa.rugby","reds.rugby"]},"type":"generic","isIDN":false,"rdapServers":["https://rdap.centralnic.com/rugby/domain/"],"rdapUpdated":1630861151662}