{"tld":"school","tldUpdated":1635292800000,"tldCreated":1423785600000,"whoisServer":["whois.nic.school"],"registry":"http://www.donuts.domains/","ianaUrl":"https://www.iana.org/domains/root/db/school.html","t":1672689370148,"version":1,"sampleDomains":{"school":["hoorakhsh.school","filimo.school","factorio.school","karo.school","analitika.school","freelancing.school","sketchvlada.school","farsi.school","bozhan.school","designwich.school","nuclio.school","11dom.school","digitalpainting.school","e2eml.school","apeiron.school","binam.school","jivegi.school","tahlil.school","orison.school","rs.school"]},"type":"generic","isIDN":false,"rdapServers":["https://rdap.donuts.co/rdap/domain/"],"rdapUpdated":1658865775758}