{"tld":"sh","tldUpdated":1600473600000,"tldCreated":874972800000,"whoisServer":["whois.nic.sh"],"registry":"http://www.nic.sh/","ianaUrl":"https://www.iana.org/domains/root/db/sh.html","t":1637870017332,"version":1,"sampleDomains":{"sh":["aii.sh","ppy.sh","123movie.sh","now.sh","surge.sh","propu.sh","odoo.sh","mexa.sh","binancezh.sh","wpu.sh","jav.sh","sta.sh","room.sh","skr.sh","cpasbien.sh","cpp.sh","hdrezka.sh","edgeme.sh","sfdc.sh","webpu.sh"],"gov.sh":["sainthelena.gov.sh","postoffice.gov.sh","audit.gov.sh"],"org.sh":["trust.org.sh"]},"type":"cctld","isIDN":false,"rdapServers":[],"rdapUpdated":1637870514247}