{"tld":"sr","tldUpdated":1583280000000,"tldCreated":683856000000,"whoisServer":[],"registry":"http://www.register.sr/","ianaUrl":"https://www.iana.org/domains/root/db/sr.html","t":1651163534804,"version":1,"sampleDomains":{"sr":["gov.sr","tripadv.sr","assuria.sr","klm.sr","self-reliance.sr","compo.sr","speedtest.sr","radio10.sr","dramacool.sr","suribet.sr","redspot.sr","vhp.sr","portal2.sr","kings.sr","keynews.sr","ubuy.sr","atv.sr","tpv.sr","google.sr","edu.sr"]},"type":"cctld","isIDN":false,"rdapServers":[],"rdapUpdated":1658865791609}