{"tld":"supply","tldUpdated":1635811200000,"tldCreated":1392249600000,"whoisServer":["whois.nic.supply"],"registry":"http://www.donuts.domains/","ianaUrl":"https://www.iana.org/domains/root/db/supply.html","t":1692610482513,"version":1,"sampleDomains":{"supply":["shopify.supply","negative.supply","resume.supply","uncrate.supply","framer.supply","vala.supply","aftermarket.supply","rl.supply","matic.supply","linktoken.supply","insights.supply","railway.supply","porno.supply","texture.supply","anima.supply","demand.supply","regus.supply","middlekid.supply","nicolaibecker.supply","24hr.supply"]},"type":"generic","isIDN":false,"rdapServers":["https://rdap.donuts.co/rdap/domain/"],"rdapUpdated":1658865795975}