{"tld":"tj","tldUpdated":1384300800000,"tldCreated":881798400000,"whoisServer":[],"registry":"http://www.nic.tj","ianaUrl":"https://www.iana.org/domains/root/db/tj.html","t":1619244894885,"version":1,"sampleDomains":{"tj":["ktm.tj","monitoring.tj","minfin.tj","sputnik.tj","nbt.tj","nafaka.tj","metaratings.tj","mix.tj","alfa.tj","parimatch.tj","belinda.tj","sahifa.tj","fft.tj","vitamin.tj","komyob.tj","kmb.tj","mfa.tj","somon.tj","dialog.tj","time.tj"],"com.tj":["google.com.tj","talco.com.tj","case.com.tj","magazin.com.tj","pkf.com.tj","fmfb.com.tj","barakat.com.tj"],"nic.tj":["www.nic.tj","ns1.nic.tj"],"gov.tj":["visa.gov.tj","zakupki.gov.tj","eprocurement.gov.tj"]},"type":"cctld","isIDN":false,"rdapServers":[],"rdapUpdated":1619246262132}