{"tld":"tw","tldUpdated":1547510400000,"tldCreated":617846400000,"whoisServer":["whois.twnic.net.tw"],"registry":"http://rs.twnic.net.tw","ianaUrl":"https://www.iana.org/domains/root/db/tw.html","t":1619244938205,"version":1,"sampleDomains":{"com.tw":["gamer.com.tw","tvbs.com.tw","ltn.com.tw","bahamut.com.tw","welltake.com.tw","twca.com.tw","likr.com.tw","buyandship.com.tw","money-link.com.tw","131.com.tw","johnford.com.tw","udn.com.tw","caocao.com.tw","book.com.tw","books.com.tw","onevision.com.tw","pokemongaole.com.tw","ctci.com.tw","emailcash.com.tw","pollster.com.tw"],"gov.tw":["npm.gov.tw","tainan.gov.tw","nat.gov.tw","moea.gov.tw","post.gov.tw","ncc.gov.tw","ntsec.gov.tw","mjib.gov.tw","ly.gov.tw","aec.gov.tw","hl.gov.tw","mnd.gov.tw","tipo.gov.tw","moeaidb.gov.tw","epa.gov.tw","president.gov.tw","cga.gov.tw","boch.gov.tw","nca.gov.tw","taichung.gov.tw"],"tw":["1337x.tw","po18.tw","popo.tw","scihubtw.tw","pttweb.tw","technews.tw","dcard.tw","likr.tw","cmoney.tw","sci-hub.tw","shopee.tw","linetv.tw","histock.tw","pimg.tw","poedb.tw","easygame.tw","apk.tw","sina.tw","bbcd.tw","dailyview.tw"],"edu.tw":["ncu.edu.tw","nkut.edu.tw","npm.edu.tw","ntu.edu.tw","ncl.edu.tw","cjcu.edu.tw","ncut.edu.tw","ydu.edu.tw","stust.edu.tw","nctu.edu.tw","ntpc.edu.tw","pccu.edu.tw","tmu.edu.tw","ntut.edu.tw","cloud.edu.tw","ndmctsgh.edu.tw","pu.edu.tw","cmu.edu.tw","mcu.edu.tw","ym.edu.tw"],"org.tw":["chinabiz.org.tw","chiuchang.org.tw","itri.org.tw","smart-grid.org.tw","tdrf.org.tw","smelearning.org.tw","anesth.org.tw","pts.org.tw","foodlabel.org.tw","food.org.tw","npf.org.tw","cpc.org.tw","nsitu.org.tw","pf.org.tw","taeanimal.org.tw","ptba.org.tw","energylabel.org.tw","zi.org.tw","narl.org.tw","tcnn.org.tw"],"net.tw":["csa.net.tw","taiwan.net.tw","match.net.tw","travel.net.tw","catch.net.tw","funfactory.net.tw","land.net.tw","myvideo.net.tw","fetc.net.tw","artlib.net.tw","seed.net.tw","mold.net.tw","taiwanstay.net.tw","b1.net.tw","hicloud.net.tw","tfn.net.tw","scientology.net.tw","ebc.net.tw","australia.net.tw","homeplus.net.tw"],"idv.tw":["takesport.idv.tw","wrestler.idv.tw","mayasky.idv.tw","speedtest.idv.tw","fase.idv.tw","buddhanet.idv.tw","meetpets.idv.tw","super.idv.tw","pilio.idv.tw","matsu.idv.tw","pheromones.idv.tw","help.idv.tw","timshan.idv.tw","shop.idv.tw","learn-house.idv.tw","ezbox.idv.tw","ph84.idv.tw","ibook.idv.tw","hoyo.idv.tw","sax.idv.tw"],"club.tw":["hd.club.tw","focus-sport.club.tw","shopping.club.tw","radio.club.tw","acg.club.tw","payeasy.club.tw","tiida.club.tw","leisure.club.tw","yoyo.club.tw","lazyweb.club.tw","shibainu.club.tw","ipv6.club.tw","nccualumni.club.tw","vectra.club.tw","ali.club.tw"],"game.tw":["auer.game.tw","more.game.tw","dreammaker.game.tw","two.game.tw","free.game.tw","rss.game.tw","sb.game.tw","apex.game.tw","anan.game.tw","vrbrothers.game.tw","pa.game.tw","artrice.game.tw","buho.game.tw"],"mil.tw":["secmail.mil.tw"],"ebiz.tw":["champion.ebiz.tw"]},"type":"cctld","isIDN":false,"rdapServers":[],"rdapUpdated":1619246286826}