{"tld":"uk","tldUpdated":1441065600000,"tldCreated":491011200000,"whoisServer":["whois.nic.uk"],"registry":"http://www.nic.uk/","ianaUrl":"https://www.iana.org/domains/root/db/uk.html","t":1614319850981,"version":1,"sampleDomains":{"co.uk":["coffeesuppliesdirect.co.uk","welcometodash.co.uk","dailymail.co.uk","adskeeper.co.uk","swingingheaven.co.uk","wayfair.co.uk","britishsurnames.co.uk","mhstar.co.uk","bbc.co.uk","gymwear.co.uk","guardianapps.co.uk","costco.co.uk","kraftburger.co.uk","ebay.co.uk","hilltrident.co.uk","pinterest.co.uk","snack-projects.co.uk","autodoc.co.uk","google.co.uk","amazon.co.uk"],"org.uk":["dulwich.org.uk","michaelkors-bags.org.uk","voidspace.org.uk","b737.org.uk","nice.org.uk","easyfundraising.org.uk","bps.org.uk","bn.org.uk","yorkshiremuseum.org.uk","volvoforums.org.uk","song-lyrics-generator.org.uk","asthma.org.uk","concrete.org.uk","nexus.org.uk","smarttransport.org.uk","name-generator.org.uk","bssa.org.uk","phrases.org.uk","doctorsoftheworld.org.uk","avif.org.uk"],"ac.uk":["ed.ac.uk","ebi.ac.uk","soton.ac.uk","imperial.ac.uk","gre.ac.uk","rcseng.ac.uk","peterborough.ac.uk","royalholloway.ac.uk","stir.ac.uk","shef.ac.uk","sheffield.ac.uk","aaschool.ac.uk","ox.ac.uk","mdx.ac.uk","port.ac.uk","london.ac.uk","core.ac.uk","leeds.ac.uk","gla.ac.uk","ucl.ac.uk"],"uk":["toomics.uk","facecrot.uk","mod.uk","fashionunited.uk","kenzato.uk","otakugamers.uk","beginnerdrums.uk","taiko.uk","1lib.uk","e2ecdn.uk","financemagazine.uk","lunneys.uk","bl.uk","wholesale-supplier.uk","ecommercedns.uk","yuzhaiwu.uk","ridgemount.uk","online-sweepstakes.uk","chatiw.uk","quackhost.uk"],"gov.uk":["hmce.gov.uk","landregistry.gov.uk","gov.uk","bis.gov.uk","data.gov.uk","ncsc.gov.uk","gateshead.gov.uk","tfl.gov.uk","discoveruni.gov.uk","plymouth.gov.uk","london-fire.gov.uk","metoffice.gov.uk","companieshouse.gov.uk","newcastle.gov.uk","nidirect.gov.uk","hambleton.gov.uk","www.gov.uk","service.gov.uk","wychavon.gov.uk","west-lindsey.gov.uk"],"net.uk":["kc.net.uk","voyager.net.uk","future.net.uk","onetel.net.uk","doctors.net.uk","gen.net.uk","paragon.net.uk","netline.net.uk","sirsidynix.net.uk","aa.net.uk","exa.net.uk","ic.net.uk","speedtest.net.uk","2020media.net.uk","giga.net.uk","zen.net.uk","eclipse.net.uk","razorblue.net.uk","guru.net.uk","jump.net.uk"],"nhs.uk":["wales.nhs.uk","leicestershospitals.nhs.uk","pastonhealthcentre.nhs.uk","111.nhs.uk","westmidlandsdeanery.nhs.uk","mft.nhs.uk","login.nhs.uk","www.nhs.uk","wwl.nhs.uk","careplus.nhs.uk","foundationprogramme.nhs.uk","addiscomberoadsurgery.nhs.uk","westsuffolkccg.nhs.uk","hee.nhs.uk","imperial.nhs.uk","sath.nhs.uk","jobs.nhs.uk","assets-staging.nhs.uk","assets.nhs.uk","digital.nhs.uk"],"me.uk":["keeping-chickens.me.uk","dewt.me.uk","massages.me.uk","cyberscore.me.uk","andybrown.me.uk","mkw.me.uk","97653.me.uk","padpad.me.uk","timestables.me.uk","xxxvideo.me.uk","obelisk.me.uk","ddns.me.uk","adolphus.me.uk","jcergolj.me.uk","speel.me.uk","tutudumonde.me.uk","timgolden.me.uk","mcdonald.me.uk","email-4.me.uk","currency.me.uk"],"ltd.uk":["augustus-oils.ltd.uk","eatdrinksleep.ltd.uk","castironradiators.ltd.uk","proauction.ltd.uk","whaleys-bradford.ltd.uk","millane.ltd.uk","uniquearts.ltd.uk","cranecare.ltd.uk","bhc.ltd.uk","limeblue.ltd.uk","constructionsolutions.ltd.uk","geeks.ltd.uk","fdsolutions.ltd.uk","4homes.ltd.uk","lloyd.ltd.uk","samoa.ltd.uk","cadar.ltd.uk","confex.ltd.uk","peri.ltd.uk","chronos.ltd.uk"],"plc.uk":["secom.plc.uk","camellia.plc.uk","phsc.plc.uk","cranswick.plc.uk","centro.plc.uk","metrobank.plc.uk","lighthousegroup.plc.uk","pcc.plc.uk","avingtrans.plc.uk","castings.plc.uk","towngate.plc.uk","seareach.plc.uk"]},"type":"cctld","isIDN":false,"rdapServers":[],"rdapUpdated":1614322592435}