{"tld":"vc","tldUpdated":1608336000000,"tldCreated":683856000000,"whoisServer":["whois2.afilias-grs.net","whois.afilias-grs.info"],"registry":false,"ianaUrl":"https://www.iana.org/domains/root/db/vc.html","t":1629744967668,"version":1,"sampleDomains":{"vc":["kahroba.vc","iser.vc","watchasian.vc","bc.vc","motivate.vc","try2services.vc","fortross.vc","vp.vc","pics.vc","gogoanime.vc","8x8.vc","nt.vc","scv.vc","topflix.vc","underscore.vc","dramacool.vc","mylink.vc","rocketship.vc","iws.vc","counter.vc"],"com.vc":["lucrum.com.vc","bp.com.vc","maisrico.com.vc","google.com.vc","orlario.com.vc","rico.com.vc","euestudo.com.vc","multilaser.com.vc","site.com.vc","conteudols.com.vc","ls.com.vc","pelomundo.com.vc","uverse.com.vc","prime.com.vc","mktdigital.com.vc","giga.com.vc","pan.com.vc","sumare.com.vc","esfera.com.vc","time.com.vc"],"gov.vc":["health.gov.vc","www.gov.vc","nationalparks.gov.vc","electoral.gov.vc","pollingstation.gov.vc","rsvgpf.gov.vc","security.gov.vc","cipo.gov.vc","customs.gov.vc","tourism.gov.vc","nemo.gov.vc","botanicalgarden.gov.vc","highcom.gov.vc","finance.gov.vc"],"org.vc":["stellar.org.vc","google.org.vc"],"net.vc":["netex24.net.vc","google.net.vc"]},"type":"cctld","isIDN":false,"rdapServers":[],"rdapUpdated":1629745656652}