{"tld":"ve","tldUpdated":1629676800000,"tldCreated":668304000000,"whoisServer":["whois.nic.ve"],"registry":"https://nic.ve/","ianaUrl":"https://www.iana.org/domains/root/db/ve.html","t":1646658983667,"version":1,"sampleDomains":{"co.ve":["paisdelosjuegos.co.ve","juegosgratis.co.ve","radio.co.ve","radios.co.ve","sandramodel.co.ve","cytotecvenezuela.co.ve","zapmeta.co.ve","municipio.co.ve","caribana.co.ve","centrocontable.co.ve","airbnb.co.ve","cari.co.ve","clasf.co.ve","trovit.co.ve","google.co.ve","psicologos.co.ve","ciudadanuncios.co.ve","atrache.co.ve","ya.co.ve","pepsico.co.ve"],"org.ve":["britishcouncil.org.ve","scc.org.ve","cienciaconciencia.org.ve","vademecumavisa.org.ve","conviteac.org.ve","patria.org.ve","bcv.org.ve","psuv.org.ve","cifar.org.ve","observatoriodeconflictos.org.ve","elsistema.org.ve","labviv.org.ve","cienciamatriarevista.org.ve","rivas.org.ve","analesdenutricion.org.ve","transparencia.org.ve","cenda.org.ve","sures.org.ve","cianz.org.ve","aiv.org.ve"],"com.ve":["banvenez.com.ve","neb.com.ve","sura.com.ve","indelma.com.ve","bancaribe.com.ve","globalhost.com.ve","enfabebe.com.ve","bod.com.ve","google.com.ve","ultimasnoticias.com.ve","mersan.com.ve","movilnet.com.ve","movistar.com.ve","cantv.com.ve","duncan.com.ve","tech-net.com.ve","firmadigital.com.ve","mercadolibre.com.ve","airtek.com.ve","mundijuegos.com.ve"],"edu.ve":["claret.edu.ve","uneweb.edu.ve","usm.edu.ve","upel.edu.ve","unimet.edu.ve","uba.edu.ve","uft.edu.ve","ujap.edu.ve","udefacampusvirtual.edu.ve","ubv.edu.ve","uny.edu.ve","ucab.edu.ve","unefa.edu.ve","cmdlt.edu.ve","unellez.edu.ve","uptos.edu.ve","uam.edu.ve","colegiosanagustin.edu.ve","iaes.edu.ve","uc.edu.ve"],"gob.ve":["sunai.gob.ve","bt.gob.ve","saren.gob.ve","maracaibo.gob.ve","sudeaseg.gob.ve","fundaproal.gob.ve","ivss.gob.ve","seniat.gob.ve","mpprijp.gob.ve","mijp.gob.ve","mppre.gob.ve","intt.gob.ve","vicepresidencia.gob.ve","corpoelec.gob.ve","fogade.gob.ve","saime.gob.ve","insai.gob.ve","cne.gob.ve","inh.gob.ve","sunagro.gob.ve"],"gov.ve":["ine.gov.ve","ivss.gov.ve","alcaldiamunicipiosucre.gov.ve","cne.gov.ve","lecheria.gov.ve","sistine.gov.ve","misionsucre.gov.ve","hidrolago.gov.ve"],"ve":["ucv.ve","ula.ve","nic.ve","usb.ve","reacciun.ve"],"net.ve":["recarga.net.ve","secretariauba.net.ve","elgrandatero.net.ve","eureka.net.ve","cardon4.net.ve","fraco.net.ve","officenet.net.ve","trv.net.ve","golddata.net.ve","netuno.net.ve","payco.net.ve","bonsaisushi.net.ve","biochrom.net.ve","universalmedicalcenter.net.ve","pcactual.net.ve","ks7000.net.ve","unefm.net.ve","campusvirtualuba.net.ve","globalhost.net.ve","concisa.net.ve"],"mil.ve":["ejercito.mil.ve","ceofanb.mil.ve","aviacion.mil.ve","armada.mil.ve","guardia.mil.ve","shn.mil.ve","dgim.mil.ve","digecafa.mil.ve","milicia.mil.ve"],"web.ve":["todoservidores.web.ve","ingenieriadigital.web.ve","com.web.ve","svmi.web.ve","alcaldia.web.ve","iutirla.web.ve","unermb.web.ve","nuevaprensa.web.ve","colegioteresianolacastellana.web.ve","gigatel.web.ve","aulavirtual.web.ve","infinitus.web.ve"],"info.ve":["avn.info.ve","tramitespublicos.info.ve","lavozdefalcon.info.ve","parroquiasantarosadelima.info.ve","dacemonagas.info.ve","ciudadmcy.info.ve","abn.info.ve","elregional.info.ve","numismatica.info.ve","bejuma.info.ve","estudioevescam.info.ve","gramscimania.info.ve","chaleleon.info.ve"],"tec.ve":["iutai.tec.ve","cuam.tec.ve"]},"type":"cctld","isIDN":false,"rdapServers":[],"rdapUpdated":1646659518654}