{"tld":"video","tldUpdated":1694476800000,"tldCreated":1418774400000,"whoisServer":["whois.nic.video"],"registry":"https://www.identity.digital/","ianaUrl":"https://www.iana.org/domains/root/db/video.html","t":1725817004234,"version":1,"sampleDomains":{"video":["assets.video","banned.video","pornhubs.video","moe.video","digiflix.video","membrana.video","ruptly.video","ixbt.video","tubi.video","idiod.video","dood.video","like.video","xh.video","oli.video","payup.video","1plus1.video","panda.video","remove.video","elements.video","nmcorp.video","grabit.video","mynakedwife.video","camwhores.video","redporn.video","mychannels.video","bongacams.video","detector.video","smiling.video","x-x-x.video","jitter.video","fushar.video","ffetish.video","incest.video","bigboss.video","pornhat.video"]},"type":"generic","isIDN":false,"rdapServers":["https://rdap.donuts.co/rdap/domain/"],"rdapUpdated":1658865827349}