{"tld":"vodka","tldUpdated":1713312000000,"tldCreated":1393545600000,"whoisServer":["whois.nic.vodka"],"registry":"http://nic.vodka/","ianaUrl":"https://www.iana.org/domains/root/db/vodka.html","t":1725817022117,"version":1,"sampleDomains":{"vodka":["upx.vodka","dixie.vodka","monkeyinparadise.vodka","dolha.vodka","logs.vodka","altadefinizione.vodka","nemiroff.vodka","faberge.vodka","moskovskaya.vodka","betdco.vodka","26000.vodka","ludan.vodka","pwo.vodka","r4a.vodka","vipbtv.vodka","vipkvy.vodka","okz.vodka","gny.vodka","steelblu.vodka","olk.vodka","9xmovies.vodka","404.vodka","loli.vodka","soap2day.vodka","fortuna.vodka","phoenix.vodka","lex.vodka","organika.vodka","lithuanian.vodka"]},"type":"generic","isIDN":false,"rdapServers":["https://rdap.nic.vodka/domain/"],"rdapUpdated":1658865830707}