{"tld":"za","tldUpdated":1579046400000,"tldCreated":657936000000,"whoisServer":[],"registry":"http://www.zadna.org.za/","ianaUrl":"https://www.iana.org/domains/root/db/za.html","t":1672689805571,"version":1,"sampleDomains":{"co.za":["bidorbuy.co.za","jobted.co.za","hostafrica.co.za","carbonite.co.za","lottoland.co.za","hadeco.co.za","supabets.co.za","interbet.co.za","adgstudios.co.za","mzansiporns.co.za","iol.co.za","google.co.za","3cx.co.za","24.co.za","pricecheck.co.za","essentiallynatural.co.za","ecosolarwarehouse.co.za","outsurance.co.za","concoursemedical.co.za","fortressofsolitude.co.za"],"ac.za":["ufs.ac.za","samrc.ac.za","ru.ac.za","uwc.ac.za","sun.ac.za","saao.ac.za","wits.ac.za","netd.ac.za","nwu.ac.za","ada.ac.za","tut.ac.za","journals.ac.za","dut.ac.za","ufh.ac.za","uct.ac.za","usaf.ac.za","uj.ac.za","ul.ac.za","cput.ac.za","up.ac.za"],"org.za":["accord.org.za","busa.org.za","arua.org.za","nsfas.org.za","huguenot.org.za","jamba.org.za","sajp.org.za","verbumetecclesia.org.za","curationis.org.za","hts.org.za","sajhivmed.org.za","rw.org.za","thejournal.org.za","sajr.org.za","sajo.org.za","sajcd.org.za","arasa.org.za","miwa.org.za","pmg.org.za","icasa.org.za"],"gov.za":["ecotp.gov.za","mpuleg.gov.za","sars.gov.za","treasury.gov.za","dhs.gov.za","mpr.gov.za","thensg.gov.za","stlm.gov.za","csd.gov.za","thedtic.gov.za","kzntreasury.gov.za","dha.gov.za","bizportal.gov.za","labour.gov.za","durban.gov.za","gtac.gov.za","parliament.gov.za","environment.gov.za","capetown.gov.za","www.gov.za"],"web.za":["printing.web.za","goodx.web.za","datacentre.web.za","exploreurbeauty.web.za","dorimankae.web.za","cari.web.za","leta.web.za","silentnight.web.za","effectualness.web.za","richmond.web.za","luodo.web.za","puffdaddy.web.za","at.web.za","furniture.web.za","g00gle.web.za","sesotho.web.za"],"net.za":["deonkrugermarketing.net.za","registry.net.za","dns.net.za","yellowpages.net.za","make.net.za","coza.net.za","accessdesign.net.za","olive.net.za","hardware.net.za","tactical.net.za","gameon.net.za","binc.net.za","sheqxpert.net.za","routeafrica.net.za","bookmaker-ratings.net.za","webhosting.net.za","winter.net.za","theentrepreneur.net.za","masseyferguson.net.za","classicinstallations.net.za"],"edu.za":["thekwini.edu.za","ctc.edu.za","sae.edu.za","ncutvet.edu.za","collegesa.edu.za","pecollege.edu.za","iie.edu.za","intec.edu.za","cjc.edu.za","cct.edu.za","kinghintsacollege.edu.za","tsc.edu.za","gscollege.edu.za","tnc.edu.za","elangeni.edu.za","eec.edu.za","kzntvet.edu.za","oxbridgeacademy.edu.za","khano.edu.za","sacap.edu.za"],"agric.za":["arc.agric.za","nda.agric.za","gadi.agric.za"],"mil.za":["navy.mil.za","af.mil.za","dod.mil.za","army.mil.za","jops.mil.za","careers.mil.za","di.mil.za"],"law.za":["miltons.law.za","ea.law.za","mpc.law.za","dvh.law.za","gvinc.law.za"],"nom.za":["www.nom.za","mp3rally.nom.za","aremaniko.nom.za","geldinvestment.nom.za","brenton.nom.za","ebookbd.nom.za","budi.nom.za","sangaga.nom.za","rohl.nom.za","doufublog.nom.za","secure.nom.za","dysonrecall.nom.za","mykakisforum.nom.za","magentoex.nom.za","bia2zirzamin30.nom.za","gtsposerzone.nom.za","coalamovies.nom.za","oishinbosoft.nom.za","desai.nom.za","faptoria.nom.za"],"school.za":["wced.school.za","pta.school.za","gp.school.za","whois.school.za"],"nic.za":["www.nic.za","nic.za","whois.nic.za"],"alt.za":["rehmet.alt.za"]},"type":"cctld","isIDN":false,"rdapServers":[],"rdapUpdated":1658865870092}